MANIFEST.in
README.rst
requirements.txt
setup.py
Flask_Boot.egg-info/PKG-INFO
Flask_Boot.egg-info/SOURCES.txt
Flask_Boot.egg-info/dependency_links.txt
Flask_Boot.egg-info/entry_points.txt
Flask_Boot.egg-info/requires.txt
Flask_Boot.egg-info/top_level.txt
flask_boot/__init__.py
flask_boot/flask_cli.py
flask_boot/project/.gitignore
flask_boot/project/README.md
flask_boot/project/manage.py
flask_boot/project/requirements.txt
flask_boot/project/wsgi.py
flask_boot/project/application/__init__.py
flask_boot/project/application/config.py
flask_boot/project/application/server.py
flask_boot/project/application/api/__init__.py
flask_boot/project/application/api/ping.py
flask_boot/project/application/api/handler/__init__.py
flask_boot/project/application/core/__init__.py
flask_boot/project/application/core/app.py
flask_boot/project/application/core/log.py
flask_boot/project/application/core/response.py
flask_boot/project/application/core/signal.py
flask_boot/project/application/exception/__init__.py
flask_boot/project/application/exception/error_code.py
flask_boot/project/application/exception/util.py
flask_boot/project/application/model/__init__.py
flask_boot/project/application/utils/__init__.py
flask_boot/project/application/utils/http.py